[{"type":"text","required":true,"label":"Name of Household Head:&nbsp;*","className":"form-control json-generated col-12","name":"name_name_of_household_head","access":false,"subtype":"text"},{"type":"textarea","required":false,"className":"form-control json-generated col-12","name":"add_address","access":false,"subtype":"textarea"},{"type":"text","required":true,"label":"Date of Birth (MM/DD/YYYY)&nbsp;*","className":"form-control json-generated col-4","name":"age_birthdate","access":false,"subtype":"text"},{"type":"text","required":true,"label":"Place of Birth&nbsp;*","className":"form-control json-generated col-4","name":"age_birthplace","access":false,"subtype":"text"},{"type":"text","required":true,"label":"Age&nbsp;*","className":"form-control json-generated col-4","name":"age_age","access":false,"subtype":"text"},{"type":"text","required":true,"label":"Occupation&nbsp;*","className":"form-control json-generated col-6","name":"age_occupation","access":false,"subtype":"text"},{"type":"text","required":true,"label":"ID Card Presented&nbsp;*","className":"form-control json-generated col-6","name":"age_id_card_presented","access":false,"subtype":"text"},{"type":"text","required":false,"className":"form-control json-generated col-3 readonly","name":"text-1683202771915-0","access":false,"value":"HOUSEHOLD MEMBERS","subtype":"text"},{"type":"text","required":false,"className":"form-control json-generated col-3 readonly","name":"text-1683202771918-0","access":false,"value":"SEX","subtype":"text"},{"type":"text","required":false,"className":"form-control json-generated col-3 readonly","name":"text-1683202724961","access":false,"value":"AGE","subtype":"text"},{"type":"text","required":false,"className":"form-control json-generated col-3 readonly","name":"text-1683202739696","access":false,"value":"RELATION TO THE HOUSEHOLD HEAD","subtype":"text"},{"type":"text","required":true,"label":"​","className":"form-control json-generated col-3","name":"house1_household1","access":false,"subtype":"text"},{"type":"text","required":false,"label":"​","className":"form-control json-generated col-3","name":"house1_sex1","access":false,"subtype":"text"},{"type":"text","required":false,"label":"​","className":"form-control json-generated col-3","name":"house1_age1","access":false,"subtype":"text"},{"type":"text","required":false,"label":"​","className":"form-control json-generated col-3","name":"house1_relation_to_the_household_head1","access":false,"subtype":"text"},{"type":"text","required":true,"label":"​","className":"form-control json-generated col-3","name":"household2_household2","access":false,"subtype":"text"},{"type":"text","required":true,"label":"​","className":"form-control json-generated col-3","name":"household2_sex2","access":false,"subtype":"text"},{"type":"text","required":true,"label":"​","className":"form-control json-generated col-3","name":"household2_age2","access":false,"subtype":"text"},{"type":"text","required":true,"label":"​","className":"form-control json-generated col-3","name":"household2_relation_to_the_household_head2","access":false,"subtype":"text"},{"type":"text","required":true,"label":"​","className":"form-control json-generated col-3","name":"household3_household3","access":false,"subtype":"text"},{"type":"text","required":true,"label":"​","className":"form-control json-generated col-3","name":"household3_sex3","access":false,"subtype":"text"},{"type":"text","required":true,"label":"​","className":"form-control json-generated col-3","name":"household3_age3","access":false,"subtype":"text"},{"type":"text","required":true,"label":"​","className":"form-control json-generated col-3","name":"household3_relation_to_the_household_head3","access":false,"subtype":"text"},{"type":"text","required":true,"label":"​","className":"form-control json-generated col-3","name":"household4_household4","access":false,"subtype":"text"},{"type":"text","required":true,"label":"​","className":"form-control json-generated col-3","name":"household4_sex4","access":false,"subtype":"text"},{"type":"text","required":true,"label":"​","className":"form-control json-generated col-3","name":"household4_age4","access":false,"subtype":"text"},{"type":"text","required":true,"label":"​","className":"form-control json-generated col-3","name":"household4_relation_to_the_household_head4","access":false,"subtype":"text"},{"type":"text","required":true,"label":"​","className":"form-control json-generated col-3","name":"household5_household5","access":false,"subtype":"text"},{"type":"text","required":true,"label":"​","className":"form-control json-generated col-3","name":"household5_sex5","access":false,"subtype":"text"},{"type":"text","required":true,"label":"​","className":"form-control json-generated col-3","name":"household5_age5","access":false,"subtype":"text"},{"type":"text","required":true,"label":"​","className":"form-control json-generated col-3","name":"household5_relation_to_the_household_head5","access":false,"subtype":"text"},{"type":"radio-group","required":false,"inline":false,"className":"json-generated","name":"a_extend_damage","access":false,"other":false,"values":[{"label":"PARTIALLY ","value":"PARTIALLY ","selected":false},{"label":"TOTALLY","value":"TOTALLY","selected":false}]},{"type":"checkbox-group","required":false,"toggle":false,"inline":false,"className":"json-generated","name":"checksignature_checkboxsign","access":false,"other":false,"values":[{"label":"By clicking this: This serves as your signature. Please review all details included in the form. ","value":"","selected":false}]},{"type":"date","required":true,"label":"Date&nbsp;*","className":"form-control json-generated col-12","name":"date_date","access":false},{"type":"header","subtype":"h4","label":"Assessment","access":false},{"type":"text","required":true,"label":"REMARKS IF ANY:&nbsp;*","className":"form-control json-generated col-12","name":"a_remarks_if_any","access":false,"subtype":"text"},{"type":"text","required":false,"label":"​<span style=\"font-size: 1rem; text-align: center; background-color: rgb(250, 250, 250); color: rgba(0, 0, 0, 0.87); font-family: Roboto, Helvetica, Arial, sans-serif; letter-spacing: 0.14994px;\">Signature Over Printed Name of LSWDO or any Authorized Government Officials</span>","className":"form-control json-generated col-12","name":"nameoflswdo_name_of_lswdo","access":false,"subtype":"text"},{"type":"date","required":false,"label":"Date","className":"form-control json-generated col-12","name":"dare_date1","access":false},{"type":"text","required":false,"label":"​<span style=\"color: rgba(0, 0, 0, 0.87); font-family: Roboto, Helvetica, Arial, sans-serif; font-size: 16px; letter-spacing: 0.14994px; text-align: center; background-color: rgb(250, 250, 250);\">Signature Over Printed Name of CSWDO or any Authorized Government Officials</span>","className":"form-control json-generated col-12","name":"name_name_of_lswdo2","access":false,"subtype":"text"},{"type":"date","required":false,"label":"Date","className":"form-control json-generated col-12","name":"date_date3","access":false}]